fsRPCClient/__init__.py
fsRPCClient/abcs.py
fsRPCClient/client.py
fsRPCClient/clientSocket.py
fsRPCClient/exceptions.py
fsRPCClient/py.typed
fsRPCClient/requestObj.py
fsRPCClient/utils.py
python_fsrpcclient-0.5.1.dist-info/LICENSE.md
python_fsrpcclient-0.5.1.dist-info/METADATA
python_fsrpcclient-0.5.1.dist-info/WHEEL
python_fsrpcclient-0.5.1.dist-info/top_level.txt
python_fsrpcclient-0.5.1.dist-info/RECORD
