Metadata-Version: 2.1
Name: python-fsrpcclient
Version: 0.5.1
Summary: Fusion Solutions RPC client
Home-page: https://github.com/FusionSolutions/python-fsrpcclient
Author: Andor `iFA` Rajci - FUSION SOLUTIONS KFT
Author-email: ifa@fusionsolutions.io
License: GPL-3
Keywords: json rpc client fusion solutions fusionsolutions
Classifier: Development Status :: 4 - Beta
Classifier: Topic :: Utilities
Classifier: Programming Language :: Python :: 3 :: Only
Classifier: Programming Language :: Python :: 3.8
Classifier: Programming Language :: Python :: 3.9
Classifier: License :: OSI Approved :: GNU Lesser General Public License v3 or later (LGPLv3+)
Requires-Python: >=3.8.0
License-File: LICENSE.md
Requires-Dist: python-fslogger ~=0.2.0
Requires-Dist: python-fssignal ~=0.1.0
Requires-Dist: python-fspacker ~=0.3.0
Requires-Dist: lz4
